AUTHORS
LICENSE
MANIFEST.in
setup.py
demo/__init__.py
demo/manage.py
demo/settings.py
demo/urls.py
demo/views.py
django_inviteme.egg-info/PKG-INFO
django_inviteme.egg-info/SOURCES.txt
django_inviteme.egg-info/dependency_links.txt
django_inviteme.egg-info/top_level.txt
docs/Makefile
docs/conf.py
docs/django-inviteme-docs-html.zip
docs/example.rst
docs/index.rst
docs/make.bat
docs/settings.rst
docs/signals.rst
docs/templates.rst
docs/templatetags.rst
docs/tutorial.rst
docs/_build/doctrees/environment.pickle
docs/_build/doctrees/example.doctree
docs/_build/doctrees/index.doctree
docs/_build/doctrees/settings.doctree
docs/_build/doctrees/signals.doctree
docs/_build/doctrees/templates.doctree
docs/_build/doctrees/templatetags.doctree
docs/_build/doctrees/tutorial.doctree
docs/_build/html/.buildinfo
docs/_build/html/django-inviteme.zip
docs/_build/html/example.html
docs/_build/html/genindex.html
docs/_build/html/index.html
docs/_build/html/objects.inv
docs/_build/html/search.html
docs/_build/html/searchindex.js
docs/_build/html/settings.html
docs/_build/html/signals.html
docs/_build/html/templates.html
docs/_build/html/templatetags.html
docs/_build/html/tutorial.html
docs/_build/html/_sources/example.txt
docs/_build/html/_sources/index.txt
docs/_build/html/_sources/settings.txt
docs/_build/html/_sources/signals.txt
docs/_build/html/_sources/templates.txt
docs/_build/html/_sources/templatetags.txt
docs/_build/html/_sources/tutorial.txt
docs/_build/html/_static/basic.css
docs/_build/html/_static/default.css
docs/_build/html/_static/doctools.js
docs/_build/html/_static/file.png
docs/_build/html/_static/jquery.js
docs/_build/html/_static/minus.png
docs/_build/html/_static/plus.png
docs/_build/html/_static/pygments.css
docs/_build/html/_static/searchtools.js
docs/_build/html/_static/sidebar.js
docs/_build/html/_static/underscore.js
inviteme/__init__.py
inviteme/admin.py
inviteme/forms.py
inviteme/models.py
inviteme/signals.py
inviteme/signed.py
inviteme/urls.py
inviteme/utils.py
inviteme/views.py
inviteme/templatetags/__init__.py
inviteme/templatetags/inviteme_tags.py
inviteme/tests/__init__.py
inviteme/tests/forms.py
