Metadata-Version: 1.0
Name: django-inviteme
Version: 1.0a2
Summary: Django invite-me form App with email verification
Home-page: http://github.com/danirus/django-inviteme/
Author: Daniel Rus Morales
Author-email: inbox@danir.us
License: MIT
Platform: UNKNOWN
Classifier: Development Status :: 4 - Beta
Classifier: Environment :: Web Environment
Classifier: Intended Audience :: Developers
Classifier: License :: OSI Approved :: MIT License
Classifier: Operating System :: OS Independent
Classifier: Programming Language :: Python
Classifier: Framework :: Django
